gsheet_pandas/__init__.py
gsheet_pandas/adapter/__init__.py
gsheet_pandas/adapter/connection.py
gsheet_pandas/asyncio/__init__.py
gsheet_pandas/asyncio/adapter/__init__.py
gsheet_pandas/asyncio/adapter/connection.py
gsheet_pandas/utils.py
gsheet_pandas-0.3.0.dist-info/METADATA
gsheet_pandas-0.3.0.dist-info/WHEEL
gsheet_pandas-0.3.0.dist-info/licenses/LICENSE
gsheet_pandas-0.3.0.dist-info/RECORD
