Metadata-Version: 2.4
Name: gsheet-pandas
Version: 0.3.0
Summary: Download and upload pandas dataframes to the Google sheets
License: MIT
License-File: LICENSE
Author: Iakov Kaiumov
Author-email: yashahelfi2012@gmail.com
Requires-Python: >=3.9,<4.0
Classifier: License :: OSI Approved :: MIT License
Classifier: Programming Language :: Python :: 3
Classifier: Programming Language :: Python :: 3.9
Classifier: Programming Language :: Python :: 3.10
Classifier: Programming Language :: Python :: 3.11
Classifier: Programming Language :: Python :: 3.12
Classifier: Programming Language :: Python :: 3.13
Classifier: Programming Language :: Python :: 3.14
Requires-Dist: aiogoogle (>=5.2.0,<6.0.0)
Requires-Dist: aiohttp (>=3.9.0,<4.0.0)
Requires-Dist: google-api-python-client (>=2.101.0,<3.0.0)
Requires-Dist: google-auth-httplib2 (>=0.1.1,<0.2.0)
Requires-Dist: google-auth-oauthlib (>=1.1.0,<2.0.0)
Requires-Dist: pandas (>=2.1.1,<3.0.0)
Requires-Dist: python-dotenv (>=1.0.0,<2.0.0)
Project-URL: homepage, https://github.com/iakov-kaiumov/gsheet-pandas
Project-URL: repository, https://github.com/iakov-kaiumov/gsheet-pandas
